aiogithubapi/__init__.py
aiogithubapi/client.py
aiogithubapi/common/__init__.py
aiogithubapi/common/const.py
aiogithubapi/common/exceptions.py
aiogithubapi/const.py
aiogithubapi/device.py
aiogithubapi/exceptions.py
aiogithubapi/github.py
aiogithubapi/graphql_examples/__init__.py
aiogithubapi/graphql_examples/repository_tags.py
aiogithubapi/helpers.py
aiogithubapi/legacy/__init__.py
aiogithubapi/legacy/client.py
aiogithubapi/legacy/device.py
aiogithubapi/legacy/github.py
aiogithubapi/legacy/helpers.py
aiogithubapi/models/__init__.py
aiogithubapi/models/base.py
aiogithubapi/models/clones.py
aiogithubapi/models/commit.py
aiogithubapi/models/contents.py
aiogithubapi/models/device_login.py
aiogithubapi/models/events.py
aiogithubapi/models/git_tree.py
aiogithubapi/models/issue.py
aiogithubapi/models/issue_comment.py
aiogithubapi/models/label.py
aiogithubapi/models/license.py
aiogithubapi/models/login_oauth.py
aiogithubapi/models/meta.py
aiogithubapi/models/milestone.py
aiogithubapi/models/organization.py
aiogithubapi/models/owner.py
aiogithubapi/models/permissions.py
aiogithubapi/models/projects.py
aiogithubapi/models/pull_request.py
aiogithubapi/models/rate_limit.py
aiogithubapi/models/reaction.py
aiogithubapi/models/release.py
aiogithubapi/models/repository.py
aiogithubapi/models/request_data.py
aiogithubapi/models/response.py
aiogithubapi/models/tag.py
aiogithubapi/models/user.py
aiogithubapi/models/views.py
aiogithubapi/namespaces/__init__.py
aiogithubapi/namespaces/base.py
aiogithubapi/namespaces/contents.py
aiogithubapi/namespaces/events.py
aiogithubapi/namespaces/git.py
aiogithubapi/namespaces/issues.py
aiogithubapi/namespaces/orgs.py
aiogithubapi/namespaces/projects.py
aiogithubapi/namespaces/pulls.py
aiogithubapi/namespaces/releases.py
aiogithubapi/namespaces/repos.py
aiogithubapi/namespaces/traffic.py
aiogithubapi/namespaces/user.py
aiogithubapi/namespaces/users.py
aiogithubapi/objects/__init__.py
aiogithubapi/objects/base.py
aiogithubapi/objects/content.py
aiogithubapi-25.5.0.dist-info/LICENSE.md
aiogithubapi-25.5.0.dist-info/METADATA
aiogithubapi-25.5.0.dist-info/WHEEL
aiogithubapi-25.5.0.dist-info/RECORD
