Metadata-Version: 2.3
Name: aiogithubapi
Version: 25.5.0
Summary: Asynchronous Python client for the GitHub API
License: MIT
Author: Ludeeus
Author-email: ludeeus@ludeeus.dev
Maintainer: Ludeeus
Maintainer-email: joasoe@proton.me
Requires-Python: >=3.9
Classifier: Intended Audience :: Developers
Classifier: License :: OSI Approved :: MIT License
Classifier: Natural Language :: English
Classifier: Programming Language :: Python :: 3
Classifier: Programming Language :: Python :: 3.9
Classifier: Programming Language :: Python :: 3.10
Classifier: Programming Language :: Python :: 3.11
Classifier: Programming Language :: Python :: 3.12
Classifier: Programming Language :: Python :: 3.13
Classifier: Topic :: Software Development :: Libraries :: Python Modules
Provides-Extra: deprecated-verify
Requires-Dist: aiohttp (>=3.8,<4.0)
Requires-Dist: async-timeout (>=5,<6)
Requires-Dist: backoff (<3)
Requires-Dist: securesystemslib (<1) ; extra == "deprecated-verify"
Requires-Dist: setuptools (>=60.0.0) ; extra == "deprecated-verify"
Requires-Dist: sigstore (<2) ; extra == "deprecated-verify"
Project-URL: Bug tracker, https://github.com/ludeeus/aiogithubapi/issues
Project-URL: Repository, https://github.com/ludeeus/aiogithubapi
